[
    {
        "id": "6b36db31bc81",
        "comments": [
            {
                "id": "2579ffddf652",
                "createdOn": "2020.10.9",
                "author": "Joseph Micla",
                "commentText": "Wow, love the blog. Great design            "
            },
            {
                "id": "fe99c2018013",
                "createdOn": "2020.10.9",
                "author": "Fiona",
                "commentText": "Agree with the last comment. best blog ever            "
            }
        ]
    }
]